MANIFEST.in
setup.cfg
setup.py
bin/confluent
confluent/__init__.py
confluent/auth.py
confluent/consoleserver.py
confluent/core.py
confluent/exceptions.py
confluent/httpapi.py
confluent/log.py
confluent/main.py
confluent/messages.py
confluent/noderange.py
confluent/shellmodule.py
confluent/sockapi.py
confluent/util.py
confluent/config/__init__.py
confluent/config/attributes.py
confluent/config/configmanager.py
confluent/interface/__init__.py
confluent/interface/console.py
confluent/plugins/configuration/__init__.py
confluent/plugins/configuration/attributes.py
confluent/plugins/hardwaremanagement/__init__.py
confluent/plugins/hardwaremanagement/ipmi.py
confluent_server.egg-info/PKG-INFO
confluent_server.egg-info/SOURCES.txt
confluent_server.egg-info/dependency_links.txt
confluent_server.egg-info/requires.txt
confluent_server.egg-info/top_level.txt
sysvinit/confluent