Metadata-Version: 1.0
Name: confluent-server
Version: 0.2.2
Summary: confluent systems management server
Home-page: http://xcat.sf.net/
Author: Jarrod Johnson
Author-email: jbjohnso@us.ibm.com
License: UNKNOWN
Platform: UNKNOWN
